scilightcon/__init__.py
scilightcon/control/__init__.py
scilightcon/datasets/__init__.py
scilightcon/datasets/_base.py
scilightcon/datasets/_logs_reader.py
scilightcon/datasets/data/Ar_lines.csv
scilightcon/datasets/data/Hg_lines.csv
scilightcon/datasets/data/Shot-to-shot_LAB4 PHAROS_25.0kHz_1030nm_InGaAs_20210917_1337.s2s
scilightcon/datasets/data/White_LED_spectrum.csv
scilightcon/datasets/data/__init__.py
scilightcon/datasets/data/atmosphere.csv
scilightcon/datasets/data/data_test_detect_peaks.csv
scilightcon/datasets/data/data_test_detect_peaks.csv.gz
scilightcon/datasets/data/data_test_detect_peaks_extracted.csv
scilightcon/datasets/data/logsreader_test.zip
scilightcon/datasets/data/reflection_EDMUND_rr_Al.csv
scilightcon/datasets/data/reflection_EDMUND_rr_Au.csv
scilightcon/datasets/data/reflection_EKSMA_Ag.csv
scilightcon/datasets/data/reflection_EKSMA_Al.csv
scilightcon/datasets/data/reflection_EKSMA_Au.csv
scilightcon/datasets/data/test_beam_profile.pkl
scilightcon/datasets/data/toolbox_materials.pkl
scilightcon/datasets/data/EO/__init__.py
scilightcon/datasets/data/EO/transmission_EO_lp_400nm.csv
scilightcon/datasets/data/EO/transmission_EO_lp_450nm.csv
scilightcon/datasets/data/EO/transmission_EO_lp_500nm.csv
scilightcon/datasets/data/EO/transmission_EO_lp_550nm.csv
scilightcon/datasets/data/EO/transmission_EO_lp_600nm.csv
scilightcon/datasets/data/EO/transmission_EO_lp_650nm.csv
scilightcon/datasets/data/EO/transmission_EO_lp_700nm.csv
scilightcon/datasets/data/EO/transmission_EO_lp_750nm.csv
scilightcon/datasets/data/EO/transmission_EO_sp_400nm.csv
scilightcon/datasets/data/EO/transmission_EO_sp_500nm.csv
scilightcon/datasets/data/EO/transmission_EO_sp_600nm.csv
scilightcon/datasets/data/EO/transmission_EO_sp_700nm.csv
scilightcon/datasets/data/thorlabs/__init__.py
scilightcon/datasets/data/thorlabs/transmission_THORLABS_DMLP425.csv
scilightcon/datasets/data/thorlabs/transmission_THORLABS_DMLP550.csv
scilightcon-0.3.2.dist-info/LICENSE
scilightcon-0.3.2.dist-info/METADATA
scilightcon-0.3.2.dist-info/WHEEL
scilightcon-0.3.2.dist-info/top_level.txt
scilightcon-0.3.2.dist-info/RECORD
