Metadata-Version: 2.1
Name: scilightcon
Version: 0.3.2
Summary: A lightcon scipack
Author: Vytautas Butkus
Author-email: vytautas.butkus@lightcon.com
Project-URL: Documentation, https://lightconupdater.blob.core.windows.net/documentation/scilightcon/index.html
Classifier: Programming Language :: Python :: 3
Classifier: License :: OSI Approved :: MIT License
Classifier: Operating System :: OS Independent
Classifier: Development Status :: 4 - Beta
Requires-Python: >=3.7
License-File: LICENSE
Requires-Dist: numpy <2.0
Requires-Dist: matplotlib
Requires-Dist: pytest
Requires-Dist: typing-extensions
Requires-Dist: scipy
Requires-Dist: pickle-mixin
Requires-Dist: msgpack
Requires-Dist: pandas
Requires-Dist: Pillow
